<?xml version="1.0" encoding="UTF-8" standalone="yes"?>
<!DOCTYPE xml>
<data-set xmlns:xsi="http://www.w3.org/2001/XMLSchema-instance">
	<header key="header">
		<rows>1</rows>
		<cols>3</cols>
		<rootPanel>HorizontalPanel</rootPanel>
		<rootCss>project-gwt-simplepanel-controlview</rootCss>
		<cssFlexTable>project-gwt-verticalpanel-controlview</cssFlexTable>
	</header>
	
	<option key="0|0">
		<widget>Button</widget>
		<label>Login Request</label>
		<css>project-gwt-button-controlview-button-0-0</css>
		<element>loginrequest</element>
		
		<cssContainer>project-gwt-button-controlview-container-0-0</cssContainer>
		
		<cssDown>project-gwt-button-controlview-button-0-0-down</cssDown>
		<cssDisable>project-gwt-button-controlview-button-0-0-disable</cssDisable>
		<tooltip>Login Request</tooltip>
		<tooltipDown>Login Request Activate</tooltipDown>
		<tooltipDisable>Login Request Disabled</tooltipDisable>
		
	</option>
	
	<option key="0|1">
		<widget>Button</widget>
		<label>Logout Request</label>
		<css>project-gwt-button-controlview-button-0-1</css>
		<element>logoutrequest</element>
		
		<cssContainer>project-gwt-button-controlview-container-0-1</cssContainer>
		
		<cssDown>project-gwt-button-controlview-button-0-1-down</cssDown>
		<cssDisable>project-gwt-button-controlview-button-0-1-disable</cssDisable>
		<tooltip>Logout Request</tooltip>
		<tooltipDown>Logout Request Activate</tooltipDown>
		<tooltipDisable>Logout Request Disabled</tooltipDisable>

	</option>
	
	<option key="0|2">
		<widget>Button</widget>
		<label>Validate Login</label>
		<css>project-gwt-button-controlview-button-0-2</css>
		<element>validatelogin</element>
		
		<cssContainer>project-gwt-button-controlview-container-0-2</cssContainer>
		
		<cssDown>project-gwt-button-controlview-button-0-2-down</cssDown>
		<cssDisable>project-gwt-button-controlview-button-0-2-disable</cssDisable>
		<tooltip>Validate Login</tooltip>
		<tooltipDown>Validate Login Activate</tooltipDown>
		<tooltipDisable>Validate Login Disabled</tooltipDisable>
	</option>
	
</data-set>