<?xml version="1.0" encoding="UTF-8" standalone="yes"?>
<!DOCTYPE xml>
<data-set xmlns:xsi="http://www.w3.org/2001/XMLSchema-instance">
	<header key="header">
		<ListConfigId>scseventList</ListConfigId>
		
		<MenuCallImageEnable>true</MenuCallImageEnable>
		<MenuCallImageLabel>alarmList_menu_call_image</MenuCallImageLabel>
		<MenuCallImageGdgAttribute>sourceID</MenuCallImageGdgAttribute>
		
		<SelectionMode>Multiple</SelectionMode>
		<DebugId>UILayoutEventSummaryViewerScsOlsListPanel</DebugId>
		<PagerName>SCADAgenPager</PagerName>
		<MwtEventBusName>scseventList</MwtEventBusName>
		<MwtEventBusScope>Global</MwtEventBusScope>
		
		<OlsCssPrefix>OLS_LIST_</OlsCssPrefix>
		<GDGAttributeString1>priority</GDGAttributeString1>
		<GDGAttributeString2>state</GDGAttributeString2>
		<GDGAttributeString3>GDGMessage03</GDGAttributeString3>
	</header>
</data-set>